{"cameraMode":{"drawMode":0,"name":"Shaded","section":"Shading Mode"},"sceneLighting":true,"audioPlay":false,"sceneViewState":{"m_AlwaysRefresh":false,"showFog":true,"showSkybox":true,"showFlares":true,"showImageEffects":true,"showParticleSystems":true,"showVisualEffectGraphs":true,"m_FxEnabled":true},"in2DMode":false,"pivot":{"x":10.11215591430664,"y":-40.495872497558597,"z":48.31644821166992},"rotation":{"x":-0.30825886130332949,"y":-0.14310631155967713,"z":0.03714246302843094,"w":-0.9430140256881714},"size":41.87910079956055,"orthographic":false}